Lab00/SRC/semaforo.v
`timescale 1ns/1ns

module semaforo (
    input  wire clk, 
    input  wire rst,
    output reg  green,
    output reg  yellow,
    output reg  red
);

    // Codificación de estados
    localparam S0 = 2'b00; // Verde (5 ciclos)
    localparam S1 = 2'b01; // Amarillo (2 ciclos)
    localparam S2 = 2'b10; // Rojo (4 ciclos)

    reg [1:0] state;
    reg [2:0] count;

    // Lógica secuencial: Transición de estados y contador
    always @(posedge clk) begin
        if (rst) begin
            state <= S0;  
            count <= 3'd0;
        end
        else begin
            case (state)
                S0: begin
                    if (count == 3'd4) begin
                        state <= S1;
                        count <= 3'd0;
                    end
                    else begin
                        count <= count + 1'b1;
                    end
                end

                S1: begin
                    if (count == 3'd1) begin
                        state <= S2;
                        count <= 3'd0;
                    end
                    else begin
                        count <= count + 1'b1;
                    end
                end

                S2: begin
                    if (count == 3'd3) begin
                        state <= S0; // Cliclo repetitivo: regresa a Verde
                        count <= 3'd0;
                    end
                    else begin
                        count <= count + 1'b1;
                    end
                end

                default: begin
                    state <= S0;
                    count <= 3'd0;
                end
            endcase
        end
    end

    // Lógica combinacional: Salidas según estado actual
    always @(*) begin
        green  = 1'b0;
        yellow = 1'b0;
        red    = 1'b0;

        case (state)
            S0: green  = 1'b1;
            S1: yellow = 1'b1;
            S2: red    = 1'b1;
            default: green = 1'b1;
        endcase
    end

endmodule

Lab00/SRC/tb_semaforo.v
`timescale 1ns/1ns

module tb_semaforo;

    reg clk;
    reg rst;

    wire green;
    wire yellow;
    wire red;

    // Instancia del módulo a probar (DUT)
    semaforo dut (
        .clk(clk),
        .rst(rst),
        .green(green),
        .yellow(yellow),
        .red(red)
    );

    // Generación de reloj (Periodo = 10ns, Frecuencia = 100MHz)
    always #5 clk = ~clk;

    initial begin
        // Inicialización de señales
        clk = 0;
        rst = 1;

        // Pulso de Reset por 10ns
        #10;
        rst = 0;

        // Tiempo suficiente para observar más de 2 ciclos completos (110ns por ciclo)
        #300;
        
        $finish;
    end

    // Generación del archivo para ondas en GTKWave
    initial begin
        $dumpfile("semaforo.vcd");
        $dumpvars(0, tb_semaforo);
    end

endmodule

Lab00/semaforo.vcd
$date
	Fri Sep 11 21:59:34 2026
$end
$version
	Icarus Verilog
$end
$timescale
	1ns
$end
$scope module tb_semaforo $end
$var wire 1 ! yellow $end
$var wire 1 " red $end
$var wire 1 # green $end
$var reg 1 $ clk $end
$var reg 1 % rst $end
$scope module dut $end
$var wire 1 $ clk $end
$var wire 1 % rst $end
$var parameter 2 & S0 $end
$var parameter 2 ' S1 $end
$var parameter 2 ( S2 $end
$var reg 3 ) count [2:0] $end
$var reg 1 # green $end
$var reg 1 " red $end
$var reg 2 * state [1:0] $end
$var reg 1 ! yellow $end
$upscope $end
$upscope $end
$enddefinitions $end
$comment Show the parameter values. $end
$dumpall
b10 (
b1 '
b0 &
$end
#0
$dumpvars
bx *
bx )
1%
0$
x#
x"
x!
$end
#5
0"
0!
1#
b0 )
b0 *
1$
#10
0$
0%
#15
b1 )
1$
#20
0$
#25
b10 )
1$
#30
0$
#35
b11 )
1$
#40
0$
#45
b100 )
1$
#50
0$
#55
1!
0#
b0 )
b1 *
1$
#60
0$
#65
b1 )
1$
#70
0$
#75
1"
0!
b0 )
b10 *
1$
#80
0$
#85
b1 )
1$
#90
0$
#95
b10 )
1$
#100
0$
#105
b11 )
1$
#110
0$
#115
1#
0"
b0 )
b0 *
1$
#120
0$
#125
b1 )
1$
#130
0$
#135
b10 )
1$
#140
0$
#145
b11 )
1$
#150
0$
#155
b100 )
1$
#160
0$
#165
1!
0#
b0 )
b1 *
1$
#170
0$
#175
b1 )
1$
#180
0$
#185
1"
0!
b0 )
b10 *
1$
#190
0$
#195
b1 )
1$
#200
0$
#205
b10 )
1$
#210
0$
#215
b11 )
1$
#220
0$
#225
1#
0"
b0 )
b0 *
1$
#230
0$
#235
b1 )
1$
#240
0$
#245
b10 )
1$
#250
0$
#255
b11 )
1$
#260
0$
#265
b100 )
1$
#270
0$
#275
1!
0#
b0 )
b1 *
1$
#280
0$
#285
b1 )
1$
#290
0$
#295
1"
0!
b0 )
b10 *
1$
#300
0$
#305
b1 )
1$
