Lab00/SRC/Acumulador.v
module acumulador (
    input  wire       clk,
    input  wire       rst,
    input  wire       start,
    input  wire [3:0] x,

    output reg  [5:0] acc,
    output reg        done
);

    // =====================================================
    // SELECCION DE VARIANTE
    // =====================================================
    // 1 = Sumar x 3 veces
    // 2 = Sumar x 4 veces
    // 3 = Sumar x hasta que acc >= 20

    localparam VARIANTE = 3;


    // =====================================================
    // ESTADOS DE LA FSM
    // =====================================================

    localparam IDLE = 2'b00;
    localparam ADD  = 2'b01;
    localparam DONE = 2'b10;

    reg [1:0] state;
    reg [1:0] next_state;


    // =====================================================
    // CONTADOR
    // =====================================================

    reg [2:0] count;


    // =====================================================
    // REGISTRO DE ESTADO
    // =====================================================

    always @(posedge clk or posedge rst) begin

        if (rst)
            state <= IDLE;
        else
            state <= next_state;

    end


    // =====================================================
    // LOGICA DE SIGUIENTE ESTADO
    // =====================================================

    always @(*) begin

        // Valor por defecto
        next_state = IDLE;

        case (state)

            // -------------------------------------------------
            // IDLE
            // -------------------------------------------------

            IDLE: begin

                if (start)
                    next_state = ADD;
                else
                    next_state = IDLE;

            end


            // -------------------------------------------------
            // ADD
            // -------------------------------------------------

            ADD: begin

                case (VARIANTE)

                    // =========================================
                    // VARIANTE 1
                    // Sumar x 3 veces
                    // =========================================

                    1: begin

                        if (count == 2)
                            next_state = DONE;
                        else
                            next_state = ADD;

                    end


                    // =========================================
                    // VARIANTE 2
                    // Sumar x 4 veces
                    // =========================================

                    2: begin

                        if (count == 3)
                            next_state = DONE;
                        else
                            next_state = ADD;

                    end


                    // =========================================
                    // VARIANTE 3
                    // Sumar x hasta que acc >= 20
                    // =========================================

                    3: begin

                        if (acc >= 20)
                            next_state = DONE;
                        else
                            next_state = ADD;

                    end


                    // =========================================
                    // OPCION NO VALIDA
                    // =========================================

                    default: begin

                        next_state = IDLE;

                    end

                endcase

            end


            // -------------------------------------------------
            // DONE
            // -------------------------------------------------

            DONE: begin

                // Después de mostrar el resultado,
                // regresar a IDLE

                next_state = IDLE;

            end


            // -------------------------------------------------
            // ESTADO NO VALIDO
            // -------------------------------------------------

            default: begin

                next_state = IDLE;

            end

        endcase

    end


    // =====================================================
    // DATAPATH
    // =====================================================

    always @(posedge clk or posedge rst) begin

        if (rst) begin

            acc   <= 6'd0;
            count <= 3'd0;

        end

        else begin

            case (state)

                // -------------------------------------------------
                // IDLE
                // -------------------------------------------------

                IDLE: begin

                    if (start) begin

                        // Primera suma directamente
                        acc   <= x;
                        count <= 3'd1;

                    end

                    else begin

                        // No hay operación:
                        // limpiar resultado anterior

                        acc   <= 6'd0;
                        count <= 3'd0;

                    end

                end


                // -------------------------------------------------
                // ADD
                // -------------------------------------------------

                ADD: begin

                    // Acumular x

                    acc   <= acc + x;
                    count <= count + 1'b1;

                end


                // -------------------------------------------------
                // DONE
                // -------------------------------------------------

                DONE: begin

                    // Mantener el resultado durante
                    // este ciclo solamente

                    acc   <= acc;
                    count <= count;

                end


                // -------------------------------------------------
                // ESTADO NO VALIDO
                // -------------------------------------------------

                default: begin

                    acc   <= 6'd0;
                    count <= 3'd0;

                end

            endcase

        end

    end


    // =====================================================
    // SALIDA DONE
    // =====================================================

    always @(*) begin

        if (state == DONE)
            done = 1'b1;
        else
            done = 1'b0;

    end

endmodule

Lab00/SRC/tb_Acumulador.v
`timescale 1ns/1ps

module tb_acumulador;

    // =====================================================
    // SEÑALES DEL TESTBENCH
    // =====================================================

    reg        clk;
    reg        rst;
    reg        start;
    reg [3:0]  x;

    wire [5:0] acc;
    wire       done;


    // =====================================================
    // INSTANCIA DEL CIRCUITO
    // =====================================================

    acumulador uut (

        .clk   (clk),
        .rst   (rst),
        .start (start),
        .x     (x),

        .acc   (acc),
        .done  (done)

    );


    // =====================================================
    // GENERADOR DE CLOCK
    // =====================================================

    always #3 clk = ~clk;


    // =====================================================
    // MONITOR
    // =====================================================

    initial begin

        $monitor(
            "Tiempo=%0t | rst=%b | start=%b | x=%d | state=%b | count=%d | acc=%d | done=%b",
            $time,
            rst,
            start,
            x,
            uut.state,
            uut.count,
            acc,
            done
        );

    end


    // =====================================================
    // GENERACION DEL ARCHIVO PARA GTKWave
    // =====================================================

    initial begin

        $dumpfile("wave.vcd");

        $dumpvars(0, tb_acumulador);

    end


    // =====================================================
    // PRUEBA
    // =====================================================

    initial begin

        // -------------------------------------------------
        // Valores iniciales
        // -------------------------------------------------

        clk   = 1'b0;
        rst   = 1'b1;
        start = 1'b0;
        x     = 4'd1;


        // -------------------------------------------------
        // Reset
        // -------------------------------------------------

        #12;

        rst = 1'b0;


        // -------------------------------------------------
        // INICIAR OPERACION
        // -------------------------------------------------

        #8;

        start = 1'b1;


        // start dura un ciclo
        #10;

        start = 1'b0;


        // -------------------------------------------------
        // Esperar resultado
        // -------------------------------------------------

        #130;


        // -------------------------------------------------
        // FINALIZAR SIMULACION
        // -------------------------------------------------

        $finish;

    end

endmodule

Lab00/wave.vcd
$date
	Fri Sep 11 23:52:07 2026
$end
$version
	Icarus Verilog
$end
$timescale
	1ps
$end
$scope module tb_acumulador $end
$var wire 1 ! done $end
$var wire 6 " acc [5:0] $end
$var reg 1 # clk $end
$var reg 1 $ rst $end
$var reg 1 % start $end
$var reg 4 & x [3:0] $end
$scope module uut $end
$var wire 1 # clk $end
$var wire 1 $ rst $end
$var wire 1 % start $end
$var wire 4 ' x [3:0] $end
$var parameter 2 ( ADD $end
$var parameter 2 ) DONE $end
$var parameter 2 * IDLE $end
$var parameter 32 + VARIANTE $end
$var reg 6 , acc [5:0] $end
$var reg 3 - count [2:0] $end
$var reg 1 ! done $end
$var reg 2 . next_state [1:0] $end
$var reg 2 / state [1:0] $end
$upscope $end
$upscope $end
$enddefinitions $end
$comment Show the parameter values. $end
$dumpall
b11 +
b0 *
b10 )
b1 (
$end
#0
$dumpvars
b0 /
b0 .
b0 -
b0 ,
b1 '
b1 &
0%
1$
0#
b0 "
0!
$end
#3000
1#
#6000
0#
#9000
1#
#12000
0#
0$
#15000
1#
#18000
0#
#20000
b1 .
1%
#21000
b1 .
b1 /
b1 -
b1 "
b1 ,
1#
#24000
0#
#27000
b1 .
b10 -
b10 "
b10 ,
1#
#30000
b1 .
0#
0%
#33000
b1 .
b11 -
b11 "
b11 ,
1#
#36000
0#
#39000
b1 .
b100 -
b100 "
b100 ,
1#
#42000
0#
#45000
b1 .
b101 -
b101 "
b101 ,
1#
#48000
0#
#51000
b1 .
b110 -
b110 "
b110 ,
1#
#54000
0#
#57000
b1 .
b111 -
b111 "
b111 ,
1#
#60000
0#
#63000
b1 .
b0 -
b1000 "
b1000 ,
1#
#66000
0#
#69000
b1 .
b1 -
b1001 "
b1001 ,
1#
#72000
0#
#75000
b1 .
b10 -
b1010 "
b1010 ,
1#
#78000
0#
#81000
b1 .
b11 -
b1011 "
b1011 ,
1#
#84000
0#
#87000
b1 .
b100 -
b1100 "
b1100 ,
1#
#90000
0#
#93000
b1 .
b101 -
b1101 "
b1101 ,
1#
#96000
0#
#99000
b1 .
b110 -
b1110 "
b1110 ,
1#
#102000
0#
#105000
b1 .
b111 -
b1111 "
b1111 ,
1#
#108000
0#
#111000
b1 .
b0 -
b10000 "
b10000 ,
1#
#114000
0#
#117000
b1 .
b1 -
b10001 "
b10001 ,
1#
#120000
0#
#123000
b1 .
b10 -
b10010 "
b10010 ,
1#
#126000
0#
#129000
b1 .
b11 -
b10011 "
b10011 ,
1#
#132000
0#
#135000
b10 .
b100 -
b10100 "
b10100 ,
1#
#138000
0#
#141000
1!
b0 .
b10 /
b101 -
b10101 "
b10101 ,
1#
#144000
0#
#147000
0!
b0 /
1#
#150000
0#
#153000
b0 -
b0 "
b0 ,
1#
