Lab00/SRC/Ejercicio 1/semaforo.v

module semaforo (
    input wire clk,
    input wire rst,
    output reg verde,
    output reg amarillo,
    output reg rojo
);

    // Codificación de estados
    localparam S_VERDE = 2'b00;
    localparam S_AMARILLO1 = 2'b01;
    localparam S_ROJO = 2'b10;
    localparam S_AMARILLO2 = 2'b11;

    // Duración de cada estado en ciclos de reloj
    localparam CICLOS_VERDE = 5;
    localparam CICLOS_AMARILLO = 2;
    localparam CICLOS_ROJO = 4;

    reg [1:0] estado_actual, estado_siguiente;
    reg [3:0] contador;


    // 1. Registro de Estado y Contador (Lógica Secuencial):

    always @(posedge clk or posedge rst) begin
        if (rst) begin
            estado_actual <= S_VERDE;
            contador      <= 4'd0;
        end else begin
            if (estado_actual != estado_siguiente) begin
                estado_actual <= estado_siguiente;
                contador      <= 4'd0;
            end else begin
                contador <= contador + 1'b1;
            end
        end
    end

    // 2. Lógica de Siguiente Estado (Lógica Combinacional):

    always @(*) begin
        estado_siguiente = estado_actual;
        case (estado_actual)
            S_VERDE: begin
                if (contador >= CICLOS_VERDE - 1)
                    estado_siguiente = S_AMARILLO1;
            end
            S_AMARILLO1: begin
                if (contador >= CICLOS_AMARILLO - 1)
                    estado_siguiente = S_ROJO;
            end
            S_ROJO: begin
                if (contador >= CICLOS_ROJO - 1)
                    estado_siguiente = S_AMARILLO2;
            end
            S_AMARILLO2: begin
                if (contador >= CICLOS_AMARILLO - 1)
                    estado_siguiente = S_VERDE;
            end
            default: estado_siguiente = S_VERDE;
        endcase
    end

    // 3. Lógica de Salidas:

    always @(*) begin
        verde    = 1'b0;
        amarillo = 1'b0;
        rojo     = 1'b0;

        case (estado_actual)
            S_VERDE:     verde    = 1'b1;
            S_AMARILLO1: amarillo = 1'b1;
            S_ROJO:      rojo     = 1'b1;
            S_AMARILLO2: amarillo = 1'b1;
            default:     verde    = 1'b1;
        endcase
    end

endmodule

Lab00/SRC/Ejercicio 1/semaforo_tb.v

`timescale 1ns / 1ps

module tb_semaforo;

    reg clk;
    reg rst;
    wire verde;
    wire amarillo;
    wire rojo;

    // Instanciación del módulo a probar (DUT)
    semaforo dut (
        .clk(clk),
        .rst(rst),
        .verde(verde),
        .amarillo(amarillo),
        .rojo(rojo)
    );

    // Reloj con período de 10 ns:
    always #5 clk = ~clk;

    initial begin
        $dumpfile("tb_semaforo.vcd");
        $dumpvars(0, tb_semaforo);

        clk = 0;
        rst = 1;

        // Liberación del Reset a los 15 ns
        #15 rst = 0;

        // Simulación durante 300 ns
        #300;

        $finish;
    end

endmodule

Lab00/SRC/Ejercicio 1/tb_semaforo.vcd
$date
	Sun Sep 20 01:00:14 2026
$end
$version
	Icarus Verilog
$end
$timescale
	1ps
$end
$scope module tb_semaforo $end
$var wire 1 ! verde $end
$var wire 1 " rojo $end
$var wire 1 # amarillo $end
$var reg 1 $ clk $end
$var reg 1 % rst $end
$scope module dut $end
$var wire 1 $ clk $end
$var wire 1 % rst $end
$var parameter 32 & CICLOS_AMARILLO $end
$var parameter 32 ' CICLOS_ROJO $end
$var parameter 32 ( CICLOS_VERDE $end
$var parameter 2 ) S_AMARILLO1 $end
$var parameter 2 * S_AMARILLO2 $end
$var parameter 2 + S_ROJO $end
$var parameter 2 , S_VERDE $end
$var reg 1 # amarillo $end
$var reg 4 - contador [3:0] $end
$var reg 2 . estado_actual [1:0] $end
$var reg 2 / estado_siguiente [1:0] $end
$var reg 1 " rojo $end
$var reg 1 ! verde $end
$upscope $end
$upscope $end
$enddefinitions $end
$comment Show the parameter values. $end
$dumpall
b0 ,
b10 +
b11 *
b1 )
b101 (
b100 '
b10 &
$end
#0
$dumpvars
b0 /
b0 .
b0 -
1%
0$
0#
0"
1!
$end
#5000
1$
#10000
0$
#15000
b1 -
1$
0%
#20000
0$
#25000
b10 -
1$
#30000
0$
#35000
b11 -
1$
#40000
0$
#45000
b1 /
b100 -
1$
#50000
0$
#55000
1#
0!
b0 -
b1 .
1$
#60000
0$
#65000
b10 /
b1 -
1$
#70000
0$
#75000
1"
0#
b0 -
b10 .
1$
#80000
0$
#85000
b1 -
1$
#90000
0$
#95000
b10 -
1$
#100000
0$
#105000
b11 /
b11 -
1$
#110000
0$
#115000
1#
0"
b0 -
b11 .
1$
#120000
0$
#125000
b0 /
b1 -
1$
#130000
0$
#135000
1!
0#
b0 -
b0 .
1$
#140000
0$
#145000
b1 -
1$
#150000
0$
#155000
b10 -
1$
#160000
0$
#165000
b11 -
1$
#170000
0$
#175000
b1 /
b100 -
1$
#180000
0$
#185000
1#
0!
b0 -
b1 .
1$
#190000
0$
#195000
b10 /
b1 -
1$
#200000
0$
#205000
1"
0#
b0 -
b10 .
1$
#210000
0$
#215000
b1 -
1$
#220000
0$
#225000
b10 -
1$
#230000
0$
#235000
b11 /
b11 -
1$
#240000
0$
#245000
1#
0"
b0 -
b11 .
1$
#250000
0$
#255000
b0 /
b1 -
1$
#260000
0$
#265000
1!
0#
b0 -
b0 .
1$
#270000
0$
#275000
b1 -
1$
#280000
0$
#285000
b10 -
1$
#290000
0$
#295000
b11 -
1$
#300000
0$
#305000
b1 /
b100 -
1$
#310000
0$
#315000
1#
0!
b0 -
b1 .
1$
