Lab00/SRC/Ejercicio 3/asm.v
`timescale 1ns / 1ps

module asm #(
    parameter CLKS_PER_BIT = 4
)(
    input  wire       clk,
    input  wire       rst,        // Entrada de reset requerida
    input  wire       start,
    input  wire [7:0] data_in,
    output reg        tx,
    output reg        busy,
    output reg        done
);

    // Codificación de estados de la FSM
    localparam IDLE       = 3'b000; // S0
    localparam LOAD       = 3'b001; // S1
    localparam BIT_HOLD   = 3'b010; // S2
    localparam SHIFT_NEXT = 3'b011; // S3
    localparam DONE       = 3'b100; // S4

    // Registros internos (Datapath y Control)
    reg [2:0]  state;
    reg [7:0]  shift_reg;
    reg [3:0]  bit_count;
    reg [15:0] tick_cnt;

    always @(posedge clk or posedge rst) begin
        if (rst) begin
            state     <= IDLE;
            shift_reg <= 8'h00;
            bit_count <= 4'd0;
            tick_cnt  <= 16'd0;
            tx        <= 1'b1;
            busy      <= 1'b0;
            done      <= 1'b0;
        end else begin
            case (state)
                IDLE: begin
                    tx   <= 1'b1;
                    busy <= 1'b0;
                    done <= 1'b0;
                    if (start) begin
                        state <= LOAD;
                        busy  <= 1'b1;
                    end
                end

                LOAD: begin
                    busy      <= 1'b1;
                    tx        <= 1'b1;
                    done      <= 1'b0;
                    shift_reg <= data_in;
                    bit_count <= 4'd0;
                    tick_cnt  <= 16'd0;
                    state     <= BIT_HOLD;
                end

                BIT_HOLD: begin
                    busy <= 1'b1;
                    done <= 1'b0;
                    tx   <= shift_reg[0];

                    if (tick_cnt >= CLKS_PER_BIT - 2) begin
                        state <= SHIFT_NEXT;
                    end else begin
                        tick_cnt <= tick_cnt + 1'b1;
                    end
                end

                SHIFT_NEXT: begin
                    busy      <= 1'b1;
                    done      <= 1'b0;
                    tx        <= shift_reg[0];
                    shift_reg <= {1'b0, shift_reg[7:1]};
                    bit_count <= bit_count + 1'b1;
                    tick_cnt  <= 16'd0;

                    if (bit_count == 4'd7) begin
                        busy  <= 1'b0;
                        state <= DONE;
                    end else begin
                        state <= BIT_HOLD;
                    end
                end

                DONE: begin
                    done  <= 1'b1;
                    tx    <= 1'b1;
                    busy  <= 1'b0;
                    state <= IDLE;
                end

                default: state <= IDLE;
            endcase
        end
    end

endmodule

Lab00/SRC/Ejercicio 3/asm_tb.v
`timescale 1ns / 1ps

module asm_tb;

    parameter CLKS_PER_BIT = 4;
    parameter CLK_PERIOD   = 10; // Reloj de 100 MHz (periodo de 10 ns)

    // Entradas al DUT
    reg       clk;
    reg       rst;
    reg       start;
    reg [7:0] data_in;

    // Salidas del DUT
    wire tx;
    wire busy;
    wire done;

    // Instanciación del módulo ASM
    asm #(
        .CLKS_PER_BIT(CLKS_PER_BIT)
    ) uut (
        .clk(clk),
        .rst(rst),
        .start(start),
        .data_in(data_in),
        .tx(tx),
        .busy(busy),
        .done(done)
    );

    // Generación de Reloj
    always #(CLK_PERIOD / 2) clk = ~clk;

    initial begin
        // 1. Nombre exacto del archivo requerido para GTKWave
        $dumpfile("wave.vcd");
        $dumpvars(0, asm_tb);

        // Inicialización de señales
        clk     = 0;
        rst     = 1;
        start   = 0;
        data_in = 8'h00;

        // Aplicar reset inicial durante 2 ciclos de reloj
        #(CLK_PERIOD * 2);
        rst = 0;
        #(CLK_PERIOD * 2);

        // ==========================================
        // Transmisión 1: Dato 8'hA5 (10100101b)
        // ==========================================
        @(posedge clk);
        data_in <= 8'hA5;
        start   <= 1'b1; // Pulso de exactamente 1 ciclo
        @(posedge clk);
        start   <= 1'b0;

        // Esperar a que se complete la transmisión 1
        wait(done == 1'b1);
        @(posedge clk);
        #(CLK_PERIOD * 4); // Intervalo de reposo entre envíos

        // ==========================================
        // Transmisión 2: Dato 8'h3C (00111100b)
        // ==========================================
        @(posedge clk);
        data_in <= 8'h3C;
        start   <= 1'b1; // Pulso de exactamente 1 ciclo
        @(posedge clk);
        start   <= 1'b0;

        // Esperar a que se complete la transmisión 2
        wait(done == 1'b1);
        @(posedge clk);
        #(CLK_PERIOD * 4);

        $display("Simulacion completada exitosamente.");
        $finish;
    end

endmodule

Lab00/SRC/Ejercicio 3/wave.vcd
$date
	Sun Sep 20 17:36:11 2026
$end
$version
	Icarus Verilog
$end
$timescale
	1ps
$end
$scope module asm_tb $end
$var wire 1 ! tx $end
$var wire 1 " done $end
$var wire 1 # busy $end
$var parameter 32 $ CLKS_PER_BIT $end
$var parameter 32 % CLK_PERIOD $end
$var reg 1 & clk $end
$var reg 8 ' data_in [7:0] $end
$var reg 1 ( rst $end
$var reg 1 ) start $end
$scope module uut $end
$var wire 1 & clk $end
$var wire 8 * data_in [7:0] $end
$var wire 1 ( rst $end
$var wire 1 ) start $end
$var parameter 3 + BIT_HOLD $end
$var parameter 32 , CLKS_PER_BIT $end
$var parameter 3 - DONE $end
$var parameter 3 . IDLE $end
$var parameter 3 / LOAD $end
$var parameter 3 0 SHIFT_NEXT $end
$var reg 4 1 bit_count [3:0] $end
$var reg 1 # busy $end
$var reg 1 " done $end
$var reg 8 2 shift_reg [7:0] $end
$var reg 3 3 state [2:0] $end
$var reg 16 4 tick_cnt [15:0] $end
$var reg 1 ! tx $end
$upscope $end
$upscope $end
$enddefinitions $end
$comment Show the parameter values. $end
$dumpall
b11 0
b1 /
b0 .
b100 -
b100 ,
b10 +
b1010 %
b100 $
$end
#0
$dumpvars
b0 4
b0 3
b0 2
b0 1
b0 *
0)
1(
b0 '
0&
0#
0"
1!
$end
#5000
1&
#10000
0&
#15000
1&
#20000
0&
0(
#25000
1&
#30000
0&
#35000
1&
#40000
0&
#45000
1)
b10100101 '
b10100101 *
1&
#50000
0&
#55000
1#
b1 3
0)
1&
#60000
0&
#65000
b10 3
b10100101 2
1&
#70000
0&
#75000
b1 4
1&
#80000
0&
#85000
b10 4
1&
#90000
0&
#95000
b11 3
1&
#100000
0&
#105000
b10 3
b0 4
b1 1
b1010010 2
1&
#110000
0&
#115000
b1 4
0!
1&
#120000
0&
#125000
b10 4
1&
#130000
0&
#135000
b11 3
1&
#140000
0&
#145000
b10 3
b0 4
b10 1
b101001 2
1&
#150000
0&
#155000
b1 4
1!
1&
#160000
0&
#165000
b10 4
1&
#170000
0&
#175000
b11 3
1&
#180000
0&
#185000
b10 3
b0 4
b11 1
b10100 2
1&
#190000
0&
#195000
b1 4
0!
1&
#200000
0&
#205000
b10 4
1&
#210000
0&
#215000
b11 3
1&
#220000
0&
#225000
b10 3
b0 4
b100 1
b1010 2
1&
#230000
0&
#235000
b1 4
1&
#240000
0&
#245000
b10 4
1&
#250000
0&
#255000
b11 3
1&
#260000
0&
#265000
b10 3
b0 4
b101 1
b101 2
1&
#270000
0&
#275000
b1 4
1!
1&
#280000
0&
#285000
b10 4
1&
#290000
0&
#295000
b11 3
1&
#300000
0&
#305000
b10 3
b0 4
b110 1
b10 2
1&
#310000
0&
#315000
b1 4
0!
1&
#320000
0&
#325000
b10 4
1&
#330000
0&
#335000
b11 3
1&
#340000
0&
#345000
b10 3
b0 4
b111 1
b1 2
1&
#350000
0&
#355000
b1 4
1!
1&
#360000
0&
#365000
b10 4
1&
#370000
0&
#375000
b11 3
1&
#380000
0&
#385000
b100 3
0#
b0 4
b1000 1
b0 2
1&
#390000
0&
#395000
b0 3
1"
1&
#400000
0&
#405000
0"
1&
#410000
0&
#415000
1&
#420000
0&
#425000
1&
#430000
0&
#435000
1&
#440000
0&
#445000
1)
b111100 '
b111100 *
1&
#450000
0&
#455000
1#
b1 3
0)
1&
#460000
0&
#465000
b10 3
b0 1
b111100 2
1&
#470000
0&
#475000
b1 4
0!
1&
#480000
0&
#485000
b10 4
1&
#490000
0&
#495000
b11 3
1&
#500000
0&
#505000
b10 3
b0 4
b1 1
b11110 2
1&
#510000
0&
#515000
b1 4
1&
#520000
0&
#525000
b10 4
1&
#530000
0&
#535000
b11 3
1&
#540000
0&
#545000
b10 3
b0 4
b10 1
b1111 2
1&
#550000
0&
#555000
b1 4
1!
1&
#560000
0&
#565000
b10 4
1&
#570000
0&
#575000
b11 3
1&
#580000
0&
#585000
b10 3
b0 4
b11 1
b111 2
1&
#590000
0&
#595000
b1 4
1&
#600000
0&
#605000
b10 4
1&
#610000
0&
#615000
b11 3
1&
#620000
0&
#625000
b10 3
b0 4
b100 1
b11 2
1&
#630000
0&
#635000
b1 4
1&
#640000
0&
#645000
b10 4
1&
#650000
0&
#655000
b11 3
1&
#660000
0&
#665000
b10 3
b0 4
b101 1
b1 2
1&
#670000
0&
#675000
b1 4
1&
#680000
0&
#685000
b10 4
1&
#690000
0&
#695000
b11 3
1&
#700000
0&
#705000
b10 3
b0 4
b110 1
b0 2
1&
#710000
0&
#715000
b1 4
0!
1&
#720000
0&
#725000
b10 4
1&
#730000
0&
#735000
b11 3
1&
#740000
0&
#745000
b10 3
b0 4
b111 1
1&
#750000
0&
#755000
b1 4
1&
#760000
0&
#765000
b10 4
1&
#770000
0&
#775000
b11 3
1&
#780000
0&
#785000
b100 3
0#
b0 4
b1000 1
1&
#790000
0&
#795000
b0 3
1!
1"
1&
#800000
0&
#805000
0"
1&
